{
    "shortNAME": "apocalyptic",
    "name": "apocalyptic super system",
    "middleNAME": "apocalyptic",
    "img": "apocaliptic.jpg",
    "link": "https://leitor.net/manga/apocalyptic-super-system/9885",
    "provLINK": "https://leitor.net",
    "prov": "leitor.net",
    "sinopse": "O fim do mundo está chegando, O terror cobrirá o mundo inteiro, e a terra se tornará uma área de caça para zumbis e mutantes. Zhao Tianlei acidentalmente obteve um misterioso o “Sistema”. Após ver a situação do mundo e a morte de seus colegas, como ele poderia ficar parado e apenas olhar? Humanos com “sistemas” e super upgrades poderiam lutar contra os cadáveres e restaurar a humanidade? 末世超级系统"
}