{
    "cod": 51,
    "shortNAME": "wonderful...",
    "name": "wonderful new world",
    "middleNAME": "wonderful...",
    "img": "desc0.jpg",
    "link": "https://leitor.net/manga/wonderful-new-world/11479",
    "provLINK": "https://leitor.net",
    "prov": "leitor.net",
    "sinopse": "Ho-Seung, um trabalhador de escritório impopular que trabalha para uma das maiores corporações da Coreia, está taxado como um pervertido porque foi acusado de instalar uma câmera escondida no banheiro feminino. Contudo, ele provou ser inocente. Então, um dia, ele foi repentinamente notificado de sua transferência pela gerente da equipe. Parecia que ela seria a vitoriosa, até..."
}